zombieBattleground/__init__.py
zombieBattleground/zombieBattleground.py
zombieBattleground-0.0.1.dist-info/LICENSE
zombieBattleground-0.0.1.dist-info/METADATA
zombieBattleground-0.0.1.dist-info/WHEEL
zombieBattleground-0.0.1.dist-info/top_level.txt
zombieBattleground-0.0.1.dist-info/RECORD
